.gitignore
.travis.yml
CHANGES.txt
CONTRIBUTORS.txt
MANIFEST.in
README.rst
bootstrap.py
buildout.cfg
collective.picturefill-configure.zcml
setup.py
travis.cfg
collective/__init__.py
collective.picturefill.egg-info/PKG-INFO
collective.picturefill.egg-info/SOURCES.txt
collective.picturefill.egg-info/dependency_links.txt
collective.picturefill.egg-info/entry_points.txt
collective.picturefill.egg-info/namespace_packages.txt
collective.picturefill.egg-info/not-zip-safe
collective.picturefill.egg-info/requires.txt
collective.picturefill.egg-info/top_level.txt
collective/picturefill/__init__.py
collective/picturefill/brain.py
collective/picturefill/common.py
collective/picturefill/configure.zcml
collective/picturefill/interfaces.py
collective/picturefill/layer.py
collective/picturefill/picturefill.min.js
collective/picturefill/picturefill.pt
collective/picturefill/picturefill_view.pt
collective/picturefill/tile.py
collective/picturefill/upgrades.py
collective/picturefill/upgrades.zcml
collective/picturefill/view.py
collective/picturefill/profiles/default/browserlayer.xml
collective/picturefill/profiles/default/jsregistry.xml
collective/picturefill/profiles/default/metadata.xml
collective/picturefill/profiles/default/registry.xml
collective/picturefill/tests/__init__.py
collective/picturefill/tests/base.py
collective/picturefill/tests/fake.py
collective/picturefill/tests/test_brain.py
collective/picturefill/tests/test_common.py
collective/picturefill/tests/test_setup.py
collective/picturefill/tests/test_tile.py
collective/picturefill/tests/test_view.py
docs/LICENSE.GPL
docs/LICENSE.txt